BldStructPred/StructPred.py
BldStructPred/__init__.py
BldStructPred/data/TrainedRF.joblib
BldStructPred/data/TrainedRF_noPOI.joblib
BldStructPred/data/TrainedRF_noPOI_numpy_v_1_26.joblib
BldStructPred/data/TrainedRF_numpy_v_1_26.joblib
BldStructPred/data/武汉建筑训练数据_POI.csv
BldStructPred/data/武汉建筑训练数据_POI_LJJ.csv
BldStructPred/data/高德POI分类与编码（中英文）_V1.06_20230208.xlsx
bldstructpred-0.2.0.dist-info/METADATA
bldstructpred-0.2.0.dist-info/WHEEL
bldstructpred-0.2.0.dist-info/licenses/LICENSE
bldstructpred-0.2.0.dist-info/RECORD
