Metadata-Version: 2.4
Name: BldStructPred
Version: 0.2.0
Summary: A trained random forest model for predicting building structural type based on building footprint, height, area, and POI
Project-URL: Homepage, https://github.com/youtian95/BldStructPred
Project-URL: Bug Tracker, https://github.com/youtian95/BldStructPred/issues
Project-URL: Changelog, https://github.com/youtian95/BldStructPred/blob/main/CHANGELOG.md
Author-email: Tian You <youtian@njtech.edu.cn>
License:                     GNU GENERAL PUBLIC LICENSE
License-File: LICENSE
Classifier: License :: OSI Approved :: MIT License
Classifier: Operating System :: OS Independent
Classifier: Programming Language :: Python :: 3
Requires-Python: >=3.12
Requires-Dist: geopandas
Requires-Dist: joblib
Requires-Dist: matplotlib
Requires-Dist: numpy
Requires-Dist: openpyxl
Requires-Dist: pandas
Requires-Dist: scikit-learn
Requires-Dist: visvalingamwyatt
